[
    {
        "updated_at": "2026-07-09 17:53:21",
        "date": "2026-07-09",
        "nav_base": 38299,
        "nav_pred": 38608.91943609855,
        "r_pred_percent": 0.8092102563997727,
        "diff_nav": 309.91943609854934,
        "acwi_percent": 0.8595328089425316,
        "fx_percent": -0.049893699823187025
    },
    {
        "updated_at": "2026-07-08 23:47:59",
        "date": "2026-07-08",
        "nav_base": 38299,
        "nav_pred": 38204.22309464701,
        "r_pred_percent": -0.24746574415257516,
        "diff_nav": -94.77690535299189,
        "acwi_percent": -0.3579271336776557,
        "fx_percent": 0.11085818103490568
    },
    {
        "updated_at": "2026-07-07 23:15:17",
        "date": "2026-07-07",
        "nav_base": 38532,
        "nav_pred": 38205.82836940239,
        "r_pred_percent": -0.8464954598712993,
        "diff_nav": -326.1716305976079,
        "acwi_percent": -0.9558742135643167,
        "fx_percent": 0.1104343673332675
    },
    {
        "updated_at": "2026-07-06 23:31:37",
        "date": "2026-07-06",
        "nav_base": 38009,
        "nav_pred": 38589.1974443753,
        "r_pred_percent": 1.5264738466555183,
        "diff_nav": 580.1974443752988,
        "acwi_percent": 1.1655506854680233,
        "fx_percent": 0.35676488561767516
    },
    {
        "updated_at": "2026-07-05 23:17:39",
        "date": "2026-07-05",
        "nav_base": 38009,
        "nav_pred": 38020.068948957145,
        "r_pred_percent": 0.02912191574928613,
        "diff_nav": 11.06894895714504,
        "acwi_percent": 0.019215206402201833,
        "fx_percent": 0.009904806118145813
    },
    {
        "updated_at": "2026-07-04 22:58:17",
        "date": "2026-07-04",
        "nav_base": 38009,
        "nav_pred": 37735.168281043225,
        "r_pred_percent": -0.7204391564018309,
        "diff_nav": -273.83171895677515,
        "acwi_percent": 0.019215206402201833,
        "fx_percent": -0.7395122639961337
    },
    {
        "updated_at": "2026-07-03 23:33:47",
        "date": "2026-07-03",
        "nav_base": 38267,
        "nav_pred": 37991.30954801971,
        "r_pred_percent": -0.7204391564018309,
        "diff_nav": -275.690451980292,
        "acwi_percent": 0.019215206402201833,
        "fx_percent": -0.7395122639961337
    },
    {
        "updated_at": "2026-07-02 23:35:57",
        "date": "2026-07-02",
        "nav_base": 38376,
        "nav_pred": 37981.184168050815,
        "r_pred_percent": -0.7468989780991087,
        "diff_nav": -285.81583194918494,
        "acwi_percent": 0.019215206402201833,
        "fx_percent": -0.7659670023608367
    }
]